pydra/tasks/templateflow/__init__.py
pydra_templateflow-0.0.2.dist-info/METADATA
pydra_templateflow-0.0.2.dist-info/WHEEL
pydra_templateflow-0.0.2.dist-info/licenses/LICENSE
pydra_templateflow-0.0.2.dist-info/RECORD
