Metadata-Version: 2.1
Name: pydra-templateflow
Version: 0.0.2
Summary: Pydra tasks for TemplateFlow
Project-URL: Documentation, https://github.com/ghisvail/pydra-templateflow#readme
Project-URL: Issues, https://github.com/ghisvail/pydra-templateflow/issues
Project-URL: Source, https://github.com/ghisvail/pydra-templateflow
Author-email: Ghislain Vaillant <ghisvail@gmail.com>
License-Expression: Apache-2.0
License-File: LICENSE
Keywords: atlas,brain,neuroimaging,pydra,reference,template,templateflow
Classifier: Development Status :: 3 - Alpha
Classifier: Intended Audience :: Science/Research
Classifier: License :: OSI Approved :: Apache Software License
Classifier: Operating System :: OS Independent
Classifier: Programming Language :: Python :: 3
Classifier: Programming Language :: Python :: 3.7
Classifier: Programming Language :: Python :: 3.8
Classifier: Programming Language :: Python :: 3.9
Classifier: Programming Language :: Python :: 3.10
Classifier: Programming Language :: Python :: 3.11
Classifier: Topic :: Scientific/Engineering
Classifier: Topic :: Software Development :: Libraries
Requires-Python: >=3.7
Requires-Dist: pydra>=0.22
Requires-Dist: templateflow>=23.0.0
